SenseAPITest.py
senseapi.py
senseapi-0.6.0.dist-info/DESCRIPTION.rst
senseapi-0.6.0.dist-info/METADATA
senseapi-0.6.0.dist-info/RECORD
senseapi-0.6.0.dist-info/WHEEL
senseapi-0.6.0.dist-info/metadata.json
senseapi-0.6.0.dist-info/top_level.txt
