Metadata-Version: 2.0
Name: senseapi
Version: 0.6.0
Summary: Library for using CommonSense API in Python applications
Home-page: https://github.com/senseobservationsystems/commonsense-python-lib
Author: Sense Observation Systems
Author-email: info@sense-os.nl
License: Apache 2.0
Keywords: sense sensor api
Platform: UNKNOWN
Requires-Dist: oauth (>=1.0.1)
